ruleset/__init__.py
ruleset-1.0.1.dist-info/DESCRIPTION.rst
ruleset-1.0.1.dist-info/METADATA
ruleset-1.0.1.dist-info/RECORD
ruleset-1.0.1.dist-info/WHEEL
ruleset-1.0.1.dist-info/metadata.json
ruleset-1.0.1.dist-info/top_level.txt
