Metadata-Version: 2.0
Name: ruleset
Version: 1.0.1
Summary: Bayesian Rule Set Mining
Home-page: https://github.com/zli37/bayesianRuleSet
Author: Zhen Li, Tong Wang
Author-email: tong-wang@uiowa.edu
License: MIT
Keywords: data mining analysis
Platform: UNKNOWN
Classifier: Development Status :: 3 - Alpha
Classifier: Intended Audience :: Developers
Classifier: Topic :: Software Development :: Build Tools
Classifier: License :: OSI Approved :: MIT License
Classifier: Programming Language :: Python :: 3.5
Requires-Python: >=3
Requires-Dist: numpy
Requires-Dist: pandas
Requires-Dist: scipy
Requires-Dist: sklearn
